django_numpy_json_encoder/__init__.py
django_numpy_json_encoder/numpy_encoder.py
django_numpy_json_encoder-0.1.3.dist-info/METADATA
django_numpy_json_encoder-0.1.3.dist-info/RECORD
django_numpy_json_encoder-0.1.3.dist-info/WHEEL
django_numpy_json_encoder-0.1.3.dist-info/top_level.txt
django_numpy_json_encoder-0.1.3.dist-info/zip-safe
